azure/mgmt/servermanager/__init__.py
azure/mgmt/servermanager/server_management.py
azure/mgmt/servermanager/version.py
azure/mgmt/servermanager/models/__init__.py
azure/mgmt/servermanager/models/encryption_jwk_resource.py
azure/mgmt/servermanager/models/encryption_jwk_resource_py3.py
azure/mgmt/servermanager/models/error.py
azure/mgmt/servermanager/models/error_py3.py
azure/mgmt/servermanager/models/gateway_parameters.py
azure/mgmt/servermanager/models/gateway_parameters_py3.py
azure/mgmt/servermanager/models/gateway_profile.py
azure/mgmt/servermanager/models/gateway_profile_py3.py
azure/mgmt/servermanager/models/gateway_resource.py
azure/mgmt/servermanager/models/gateway_resource_paged.py
azure/mgmt/servermanager/models/gateway_resource_py3.py
azure/mgmt/servermanager/models/gateway_status.py
azure/mgmt/servermanager/models/gateway_status_py3.py
azure/mgmt/servermanager/models/node_parameters.py
azure/mgmt/servermanager/models/node_parameters_py3.py
azure/mgmt/servermanager/models/node_resource.py
azure/mgmt/servermanager/models/node_resource_paged.py
azure/mgmt/servermanager/models/node_resource_py3.py
azure/mgmt/servermanager/models/power_shell_command_parameters.py
azure/mgmt/servermanager/models/power_shell_command_parameters_py3.py
azure/mgmt/servermanager/models/power_shell_command_result.py
azure/mgmt/servermanager/models/power_shell_command_result_py3.py
azure/mgmt/servermanager/models/power_shell_command_results.py
azure/mgmt/servermanager/models/power_shell_command_results_py3.py
azure/mgmt/servermanager/models/power_shell_command_status.py
azure/mgmt/servermanager/models/power_shell_command_status_py3.py
azure/mgmt/servermanager/models/power_shell_session_resource.py
azure/mgmt/servermanager/models/power_shell_session_resource_py3.py
azure/mgmt/servermanager/models/power_shell_session_resources.py
azure/mgmt/servermanager/models/power_shell_session_resources_py3.py
azure/mgmt/servermanager/models/power_shell_tab_completion_parameters.py
azure_mgmt_servermanager-2.0.1.dist-info/LICENSE
azure_mgmt_servermanager-2.0.1.dist-info/METADATA
azure_mgmt_servermanager-2.0.1.dist-info/WHEEL
azure_mgmt_servermanager-2.0.1.dist-info/top_level.txt
azure_mgmt_servermanager-2.0.1.dist-info/RECORD
